mean.v
module mean(rst, clk, in, mean);
input rst, clk;
input [3:0] in;
output reg [3:0] mean;

reg [3:0] x0, x1, x2, x3;
wire [5:0] sum;
wire [3:0] m_tmp;

always@(posedge clk or posedge rst)
begin 
	if (rst) {x3,x2,x1,x0}<=16'd0;
	else
	begin
		x3<=x2;
		x2<=x1;
		x1<=x0;
		x0<=in;
	end
end
assign sum = (x0+x1)+(x2+x3);
assign m_tmp = sum >> 2;
//assign m_tmp = sum[5:2];

always@(posedge clk or posedge rst)
begin	
	if (rst) mean <= 4'd0;
	else mean <=m_tmp;
end
endmodule

mean_tb.v
`timescale 1ns/100ps

module mean_tb;

//input
reg rst, clk;
reg [3:0] in;

//output
wire [3:0] mean;

mean m1(.rst(rst),
				.clk(clk),
				.in(in),
				.mean(mean));

//input signal clk
initial #0 clk = 1'b0;
always #5 clk = ~clk;

//input signal rst,in

initial
begin
$dumpfile("mean_tb.vcd");
$dumpvars(0,mean_tb);
end

initial
begin:in_set_blk
	integer i;
	integer seed1;
	#0 rst = 1'b0;
		 in = 4'b0;
	#10 rst = 1'b1;
	#10 rst = 1'b0;
	seed1 = 1;
	for (i=0;i<100;i=i+1)
		begin 
		in = $random(seed1);
		#10 $display($time,"in=%d,mean=%d\n",in,mean);
				$display($time,"x0=%d,x1=%d,x2=%d,x3=%d\n",
											m1.x0,m1.x1,m1.x2,m1.x3);
				$display($time,"m_tmp=%d\n",m1.m_tmp);
		end
		#10 $finish; 
end
endmodule

mean_tb.vcd
$date
	Sun Jul 24 22:31:15 2022
$end
$version
	Icarus Verilog
$end
$timescale
	100ps
$end
$scope module mean_tb $end
$var wire 4 ! mean [3:0] $end
$var reg 1 " clk $end
$var reg 4 # in [3:0] $end
$var reg 1 $ rst $end
$scope module m1 $end
$var wire 1 " clk $end
$var wire 4 % in [3:0] $end
$var wire 1 $ rst $end
$var wire 6 & sum [5:0] $end
$var wire 4 ' m_tmp [3:0] $end
$var reg 4 ( mean [3:0] $end
$var reg 4 ) x0 [3:0] $end
$var reg 4 * x1 [3:0] $end
$var reg 4 + x2 [3:0] $end
$var reg 4 , x3 [3:0] $end
$upscope $end
$scope begin in_set_blk $end
$var integer 32 - i [31:0] $end
$var integer 32 . seed1 [31:0] $end
$upscope $end
$upscope $end
$enddefinitions $end
#0
$dumpvars
bx .
bx -
bx ,
bx +
bx *
bx )
bx (
bx '
bx &
b0 %
0$
b0 #
0"
bx !
$end
#50
b0 )
1"
#100
b0 '
b0 !
b0 (
b0 &
b0 ,
b0 +
b0 *
0"
1$
#150
1"
#200
0"
b0 -
b10000110111001110 .
0$
#250
1"
#300
0"
b1000 #
b1000 %
b11100010110011000001111110111 .
b1 -
#350
b10 '
b1000 &
b1000 )
1"
#400
0"
b110 #
b110 %
b11000011010110010011011111001100 .
b10 -
#450
b11 '
b10 !
b10 (
b110 )
b1110 &
b1000 *
1"
#500
0"
b1100 #
b1100 %
b101110000100110000101001011101 .
b11 -
#550
b110 '
b1100 )
b110 *
b11010 &
b1000 +
b11 !
b11 (
1"
#600
0"
b1110 #
b1110 %
b11100111001000110000010101111010 .
b100 -
#650
b1010 '
b110 !
b110 (
b1110 )
b1100 *
b110 +
b101000 &
b1000 ,
1"
#700
0"
b111 #
b111 %
b11100011110011001001010010110011 .
b101 -
#750
b1001 '
b111 )
b1110 *
b1100 +
b100111 &
b110 ,
b1010 !
b1010 (
1"
#800
0"
b110 #
b110 %
b1100011000100110010101001011000 .
b110 -
#850
b1001 !
b1001 (
b110 )
b111 *
b1110 +
b100111 &
b1100 ,
1"
#900
0"
b11 #
b11 %
b1111001110101110110000001111001 .
b111 -
#950
b111 '
b11 )
b110 *
b111 +
b11110 &
b1110 ,
1"
#1000
0"
b11100001110101110110010111100110 .
b1000 -
#1050
b100 '
b111 !
b111 (
b11 *
b110 +
b10011 &
b111 ,
1"
#1100
0"
b1111 #
b1111 %
b101111100011110100011100101111 .
b1001 -
#1150
b110 '
b1111 )
b11 +
b11011 &
b110 ,
b100 !
b100 (
1"
#1200
0"
b111 #
b111 %
b10100011100010000110001110100100 .
b1010 -
#1250
b111 '
b110 !
b110 (
b111 )
b1111 *
b11100 &
b11 ,
1"
#1300
0"
b1001 #
b1001 %
b1000100111010110001111001010101 .
b1011 -
#1350
b1000 '
b1001 )
b111 *
b100010 &
b1111 +
b111 !
b111 (
1"
#1400
0"
b1110 #
b1110 %
b111111001001101001101100010010 .
b1100 -
#1450
b1011 '
b1000 !
b1000 (
b1110 )
b1001 *
b111 +
b101101 &
b1111 ,
1"
#1500
0"
b101 #
b101 %
b100010110111000001011101101011 .
b1101 -
#1550
b1000 '
b101 )
b1110 *
b1001 +
b100011 &
b111 ,
b1011 !
b1011 (
1"
#1600
0"
b1101 #
b1101 %
b101110110110100010111110110000 .
b1110 -
#1650
b1010 '
b1000 !
b1000 (
b1101 )
b101 *
b1110 +
b101001 &
b1001 ,
1"
#1700
0"
b1 #
b1 %
b11001000110101000001111111110001 .
b1111 -
#1750
b1000 '
b1 )
b1101 *
b101 +
b100001 &
b1110 ,
b1010 !
b1010 (
1"
#1800
0"
b1110 #
b1110 %
b10110111011011011101000011111110 .
b10000 -
#1850
b1000 !
b1000 (
b1110 )
b1 *
b1101 +
b100001 &
b101 ,
1"
#1900
0"
b1111 #
b1111 %
b1000111100010110100000101100111 .
b10001 -
#1950
b1010 '
b1111 )
b1110 *
b1 +
b101011 &
b1101 ,
1"
#2000
0"
b1100 #
b1100 %
b10011110001111001001101001111100 .
b10010 -
#2050
b1010 !
b1010 (
b1100 )
b1111 *
b1110 +
b101010 &
b1 ,
1"
#2100
0"
b1001 #
b1001 %
b1100100110111000000000101001101 .
b10011 -
#2150
b1100 '
b1001 )
b1100 *
b1111 +
b110010 &
b1110 ,
1"
#2200
0"
b11 #
b11 %
b11110001100010101111001110101010 .
b10100 -
#2250
b1001 '
b1100 !
b1100 (
b11 )
b1001 *
b1100 +
b100111 &
b1111 ,
1"
#2300
0"
b1100 #
b1100 %
b1101110010011101100000100100011 .
b10101 -
#2350
b1100 )
b11 *
b1001 +
b100100 &
b1100 ,
b1001 !
b1001 (
1"
#2400
0"
b10110000000100111000000001000 .
b10110 -
#2450
b1100 *
b11 +
b100100 &
b1001 ,
1"
#2500
0"
b1111 #
b1111 %
b101111101011000001111001101001 .
b10111 -
#2550
b1010 '
b1111 )
b1100 +
b101010 &
b11 ,
1"
#2600
0"
b1 #
b1 %
b1000110010001010111100010110 .
b11000 -
#2650
b1010 !
b1010 (
b1 )
b1111 *
b101000 &
b1100 ,
1"
#2700
0"
b11101000101011100101001010011111 .
b11001 -
#2750
b111 '
b1 *
b11101 &
b1111 +
1"
#2800
0"
b0 #
b0 %
b10000000011010010011110001010100 .
b11010 -
#2850
b100 '
b111 !
b111 (
b0 )
b1 +
b10001 &
b1111 ,
1"
#2900
0"
b1 #
b1 %
b1101000101010011001001101000101 .
b11011 -
#2950
b0 '
b1 )
b0 *
b11 &
b1 ,
b100 !
b100 (
1"
#3000
0"
b1111 #
b1111 %
b11111111100010100110111101000010 .
b11100 -
#3050
b100 '
b0 !
b0 (
b1111 )
b1 *
b10001 &
b0 +
1"
#3100
0"
b1 #
b1 %
b11000110000110111000111011011 .
b11101 -
#3150
b1 )
b1111 *
b1 +
b10001 &
b0 ,
b100 !
b100 (
1"
#3200
0"
b110 #
b110 %
b110011001001010100101101100000 .
b11110 -
#3250
b101 '
b110 )
b1 *
b1111 +
b10111 &
b1 ,
1"
#3300
0"
b1010 #
b1010 %
b100101000100010011101111100001 .
b11111 -
#3350
b1000 '
b1010 )
b110 *
b1 +
b100000 &
b1111 ,
b101 !
b101 (
1"
#3400
0"
b101 #
b101 %
b11001010101110000110000000101110 .
b100000 -
#3450
b101 '
b1000 !
b1000 (
b101 )
b1010 *
b110 +
b10110 &
b1 ,
1"
#3500
0"
b10010101101010101101011010111 .
b100001 -
#3550
b110 '
b101 *
b1010 +
b11010 &
b110 ,
b101 !
b101 (
1"
#3600
0"
b111 #
b111 %
b10001011101011011010100100101100 .
b100010 -
#3650
b110 !
b110 (
b111 )
b101 +
b11011 &
b1010 ,
1"
#3700
0"
b1001 #
b1001 %
b1010100110100111011010000111101 .
b100011 -
#3750
b1001 )
b111 *
b11010 &
b101 ,
1"
#3800
0"
b11 #
b11 %
b1100001111010110110110111011010 .
b100100 -
#3850
b11 )
b1001 *
b11000 &
b111 +
1"
#3900
0"
b111 #
b111 %
b11001011111101010000100110010011 .
b100101 -
#3950
b111 )
b11 *
b1001 +
b11010 &
b111 ,
1"
#4000
0"
b1100 #
b1100 %
b11001110010010000010000110111000 .
b100110 -
#4050
b111 '
b1100 )
b111 *
b11 +
b11111 &
b1001 ,
1"
#4100
0"
b110 #
b110 %
b11111011001100010101100001011001 .
b100111 -
#4150
b110 )
b1100 *
b111 +
b11100 &
b11 ,
b111 !
b111 (
1"
#4200
0"
b0 #
b0 %
b10110010100010001000110 .
b101000 -
#4250
b110 '
b0 )
b110 *
b1100 +
b11001 &
b111 ,
1"
#4300
0"
b1000 #
b1000 %
b10100001110010011101000001111 .
b101001 -
#4350
b1000 )
b0 *
b110 +
b11010 &
b1100 ,
b110 !
b110 (
1"
#4400
0"
b111 #
b111 %
b1010011110101010100000100000100 .
b101010 -
#4450
b101 '
b111 )
b1000 *
b0 +
b10101 &
b110 ,
1"
#4500
0"
b1110 #
b1110 %
b110111000101100100010000110101 .
b101011 -
#4550
b111 '
b1110 )
b111 *
b1000 +
b11101 &
b0 ,
b101 !
b101 (
1"
#4600
0"
b101 #
b101 %
b10000010100000000100111101110010 .
b101100 -
#4650
b1000 '
b111 !
b111 (
b101 )
b1110 *
b111 +
b100010 &
b1000 ,
1"
#4700
0"
b1000 #
b1000 %
b1010100001110100110100001001011 .
b101101 -
#4750
b1000 )
b101 *
b1110 +
b100010 &
b111 ,
b1000 !
b1000 (
1"
#4800
0"
b100 #
b100 %
b11010010010111000101001100010000 .
b101110 -
#4850
b111 '
b100 )
b1000 *
b101 +
b11111 &
b1110 ,
1"
#4900
0"
b1110 #
b1110 %
b1110111001101100101001111010001 .
b101111 -
#4950
b1110 )
b100 *
b1000 +
b11111 &
b101 ,
b111 !
b111 (
1"
#5000
0"
b1001 #
b1001 %
b10001100100100111011101101011110 .
b110000 -
#5050
b1000 '
b1001 )
b1110 *
b100 +
b100011 &
b1000 ,
1"
#5100
0"
b1100 #
b1100 %
b11001110001011101101000001000111 .
b110001 -
#5150
b1001 '
b1100 )
b1001 *
b1110 +
b100111 &
b100 ,
b1000 !
b1000 (
1"
#5200
0"
b1000 #
b1000 %
b1001100010101110110001111011100 .
b110010 -
#5250
b1010 '
b1001 !
b1001 (
b1000 )
b1100 *
b1001 +
b101011 &
b1110 ,
1"
#5300
0"
b1011 #
b1011 %
b11110101111010010010001100101101 .
b110011 -
#5350
b1011 )
b1000 *
b1100 +
b101000 &
b1001 ,
b1010 !
b1010 (
1"
#5400
0"
b11100101101001110111010000001010 .
b110100 -
#5450
b1011 *
b1000 +
b101010 &
b1100 ,
1"
#5500
0"
b1000 #
b1000 %
b11011100000001100110111000000011 .
b110101 -
#5550
b1001 '
b1000 )
b1011 +
b100110 &
b1000 ,
1"
#5600
0"
b101 #
b101 %
b11110010101111110011111101101000 .
b110110 -
#5650
b1000 '
b1001 !
b1001 (
b101 )
b1000 *
b100011 &
b1011 ,
1"
#5700
0"
b1 #
b1 %
b1011000110001100000111001001001 .
b110111 -
#5750
b110 '
b1 )
b101 *
b11001 &
b1000 +
b1000 !
b1000 (
1"
#5800
0"
b111 #
b111 %
b110011100111000010010101110110 .
b111000 -
#5850
b101 '
b110 !
b110 (
b111 )
b1 *
b101 +
b10101 &
b1000 ,
1"
#5900
0"
b1110 #
b1110 %
b1100111011001101111110101111111 .
b111001 -
#5950
b110 '
b1110 )
b111 *
b1 +
b11011 &
b101 ,
b101 !
b101 (
1"
#6000
0"
b1011 #
b1011 %
b101110101110111000110110100 .
b111010 -
#6050
b1000 '
b110 !
b110 (
b1011 )
b1110 *
b111 +
b100001 &
b1 ,
1"
#6100
0"
b0 #
b0 %
b10000000000000011000100100101 .
b111011 -
#6150
b0 )
b1011 *
b1110 +
b100000 &
b111 ,
b1000 !
b1000 (
1"
#6200
0"
b111 #
b111 %
b11110010110011101110100010 .
b111100 -
#6250
b111 )
b0 *
b1011 +
b100000 &
b1110 ,
1"
#6300
0"
b1110 #
b1110 %
b10010111011001111111101010111011 .
b111101 -
#6350
b1110 )
b111 *
b0 +
b100000 &
b1011 ,
1"
#6400
0"
b1 #
b1 %
b10000000101110100100011011000000 .
b111110 -
#6450
b101 '
b1 )
b1110 *
b111 +
b10110 &
b0 ,
1"
#6500
0"
b11 #
b11 %
b11010001100000100110011111000001 .
b111111 -
#6550
b110 '
b11 )
b1 *
b1110 +
b11001 &
b111 ,
b101 !
b101 (
1"
#6600
0"
b1000 #
b1000 %
b11001100011100101110001010001110 .
b1000000 -
#6650
b110 !
b110 (
b1000 )
b11 *
b1 +
b11010 &
b1110 ,
1"
#6700
0"
b0 #
b0 %
b1110000000011101010000110110111 .
b1000001 -
#6750
b11 '
b0 )
b1000 *
b11 +
b1100 &
b1 ,
1"
#6800
0"
b111 #
b111 %
b11011101001001100101010001100 .
b1000010 -
#6850
b100 '
b11 !
b11 (
b111 )
b0 *
b1000 +
b10010 &
b11 ,
1"
#6900
0"
b1001011110010110100111000011101 .
b1000011 -
#6950
b101 '
b111 *
b0 +
b10110 &
b1000 ,
b100 !
b100 (
1"
#7000
0"
b101 #
b101 %
b1010010111000100000011000111010 .
b1000100 -
#7050
b100 '
b101 !
b101 (
b101 )
b111 +
b10011 &
b0 ,
1"
#7100
0"
b1111 #
b1111 %
b11011111100010011110111001110011 .
b1000101 -
#7150
b1000 '
b1111 )
b101 *
b100010 &
b111 ,
b100 !
b100 (
1"
#7200
0"
b10 #
b10 %
b11110001000000101100100100011000 .
b1000110 -
#7250
b111 '
b1000 !
b1000 (
b10 )
b1111 *
b11101 &
b101 +
1"
#7300
0"
b1001 #
b1001 %
b11101100100010010100000000111001 .
b1000111 -
#7350
b1001 )
b10 *
b1111 +
b11111 &
b101 ,
b111 !
b111 (
1"
#7400
0"
b100 #
b100 %
b10100010011001000101001010100110 .
b1001000 -
#7450
b100 )
b1001 *
b10 +
b11110 &
b1111 ,
1"
#7500
0"
b1010 #
b1010 %
b1110101001011101001110011101111 .
b1001001 -
#7550
b110 '
b1010 )
b100 *
b1001 +
b11001 &
b10 ,
1"
#7600
0"
b10 #
b10 %
b11010001001110101100111001100100 .
b1001010 -
#7650
b110 !
b110 (
b10 )
b1010 *
b100 +
b11001 &
b1001 ,
1"
#7700
0"
b1101 #
b1101 %
b1010110111101100101101000010101 .
b1001011 -
#7750
b111 '
b1101 )
b10 *
b1010 +
b11101 &
b100 ,
1"
#7800
0"
b1111 #
b1111 %
b1111111111011100011001111010010 .
b1001100 -
#7850
b1010 '
b111 !
b111 (
b1111 )
b1101 *
b10 +
b101000 &
b1010 ,
1"
#7900
0"
b1100 #
b1100 %
b10111110001100110010100100101011 .
b1001101 -
#7950
b1100 )
b1111 *
b1101 +
b101010 &
b10 ,
b1010 !
b1010 (
1"
#8000
0"
b10 #
b10 %
b10001001110100010011001110000 .
b1001110 -
#8050
b10 )
b1100 *
b1111 +
b101010 &
b1101 ,
1"
#8100
0"
b1011 #
b1011 %
b11100101111101000111011110110001 .
b1001111 -
#8150
b1011 )
b10 *
b1100 +
b101000 &
b1111 ,
1"
#8200
0"
b1101 #
b1101 %
b110100010001101010110111110 .
b1010000 -
#8250
b1001 '
b1101 )
b1011 *
b10 +
b100110 &
b1100 ,
1"
#8300
0"
b1000 #
b1000 %
b100001010111100111100100111 .
b1010001 -
#8350
b1000 '
b1000 )
b1101 *
b1011 +
b100010 &
b10 ,
b1001 !
b1001 (
1"
#8400
0"
b1111 #
b1111 %
b1011111110000001101110100111100 .
b1010010 -
#8450
b1011 '
b1000 !
b1000 (
b1111 )
b1000 *
b1101 +
b101111 &
b1011 ,
1"
#8500
0"
b1011 #
b1011 %
b1010101111010010011010100001101 .
b1010011 -
#8550
b1011 )
b1111 *
b1000 +
b101111 &
b1101 ,
b1011 !
b1011 (
1"
#8600
0"
b0 #
b0 %
b11011000011111100010010001101010 .
b1010100 -
#8650
b1000 '
b0 )
b1011 *
b1111 +
b100010 &
b1000 ,
1"
#8700
0"
b10 #
b10 %
b11101001010001101000101011100011 .
b1010101 -
#8750
b111 '
b10 )
b0 *
b1011 +
b11100 &
b1111 ,
b1000 !
b1000 (
1"
#8800
0"
b1010 #
b1010 %
b11101101011011011011111011001000 .
b1010110 -
#8850
b101 '
b111 !
b111 (
b1010 )
b10 *
b0 +
b10111 &
b1011 ,
1"
#8900
0"
b100 #
b100 %
b1110010010110011110111000101001 .
b1010111 -
#8950
b100 '
b100 )
b1010 *
b10 +
b10000 &
b0 ,
b101 !
b101 (
1"
#9000
0"
b10 #
b10 %
b10001010001001100101111010110 .
b1011000 -
#9050
b100 !
b100 (
b10 )
b100 *
b1010 +
b10010 &
b10 ,
1"
#9100
0"
b1100 #
b1100 %
b11110010001110001100001011111 .
b1011001 -
#9150
b111 '
b1100 )
b10 *
b100 +
b11100 &
b1010 ,
1"
#9200
0"
b111 #
b111 %
b11110011100010100101011100010100 .
b1011010 -
#9250
b110 '
b111 !
b111 (
b111 )
b1100 *
b10 +
b11001 &
b100 ,
1"
#9300
0"
b110 #
b110 %
b1100011010001111011111100000101 .
b1011011 -
#9350
b110 )
b111 *
b1100 +
b11011 &
b10 ,
b110 !
b110 (
1"
#9400
0"
b1000 #
b1000 %
b11100100001011000011100000000010 .
b1011100 -
#9450
b1000 '
b1000 )
b110 *
b111 +
b100001 &
b1100 ,
1"
#9500
0"
b1100 #
b1100 %
b101110010000101111001110011011 .
b1011101 -
#9550
b1100 )
b1000 *
b110 +
b100001 &
b111 ,
b1000 !
b1000 (
1"
#9600
0"
b1011 #
b1011 %
b1100101100101101111001000100000 .
b1011110 -
#9650
b1001 '
b1011 )
b1100 *
b1000 +
b100101 &
b110 ,
1"
#9700
0"
b1100 #
b1100 %
b11110110010010111000001110100001 .
b1011111 -
#9750
b1010 '
b1100 )
b1011 *
b1100 +
b101011 &
b1000 ,
b1001 !
b1001 (
1"
#9800
0"
b111 #
b111 %
b10010011110010001001010011101110 .
b1100000 -
#9850
b1010 !
b1010 (
b111 )
b1100 *
b1011 +
b101010 &
b1100 ,
1"
#9900
0"
b1000 #
b1000 %
b11100000111010101100010010111 .
b1100001 -
#9950
b1001 '
b1000 )
b111 *
b1100 +
b100110 &
b1011 ,
1"
#10000
0"
b11 #
b11 %
b1011001100101101001101111101100 .
b1100010 -
#10050
b111 '
b1001 !
b1001 (
b11 )
b1000 *
b111 +
b11110 &
b1100 ,
1"
#10100
0"
b1110 #
b1110 %
b11111111011100011101011111111101 .
b1100011 -
#10150
b1000 '
b1110 )
b11 *
b1000 +
b100000 &
b111 ,
b111 !
b111 (
1"
#10200
0"
b1100100 -
#10250
b1001 '
b1000 !
b1000 (
b1110 *
b11 +
b100111 &
b1000 ,
1"
