tb.v
module tb;

reg       clk;
reg       rstn;
reg [5:0] cnt;

always #5 clk = ~clk;

always @(posedge clk or negedge rstn)begin
    if(!rstn)
        cnt <= 6'h0;
    else
        cnt <= cnt + 6'h1;
end

initial begin
    clk  = 1'b0;
    rstn = 1'b1;
    #10;
    rstn = 1'b0;
    #10;
    rstn = 1'b1;
    $display("Hello ICARUS verilog!");
    #1000;
    $finish;
end

always @(cnt)begin
    $display("%0t, cnt=%d",$time,cnt);
end

initial
begin
   $dumpfile("tb.vcd");
   $dumpvars(0,tb);
end

endmodule

tb.vcd
$date
	Sun Jul  3 01:45:46 2022
$end
$version
	Icarus Verilog
$end
$timescale
	1s
$end
$scope module tb $end
$var reg 1 ! clk $end
$var reg 6 " cnt [5:0] $end
$var reg 1 # rstn $end
$upscope $end
$enddefinitions $end
#0
$dumpvars
1#
bx "
0!
$end
#5
1!
#10
b0 "
0!
0#
#15
1!
#20
0!
1#
#25
b1 "
1!
#30
0!
#35
b10 "
1!
#40
0!
#45
b11 "
1!
#50
0!
#55
b100 "
1!
#60
0!
#65
b101 "
1!
#70
0!
#75
b110 "
1!
#80
0!
#85
b111 "
1!
#90
0!
#95
b1000 "
1!
#100
0!
#105
b1001 "
1!
#110
0!
#115
b1010 "
1!
#120
0!
#125
b1011 "
1!
#130
0!
#135
b1100 "
1!
#140
0!
#145
b1101 "
1!
#150
0!
#155
b1110 "
1!
#160
0!
#165
b1111 "
1!
#170
0!
#175
b10000 "
1!
#180
0!
#185
b10001 "
1!
#190
0!
#195
b10010 "
1!
#200
0!
#205
b10011 "
1!
#210
0!
#215
b10100 "
1!
#220
0!
#225
b10101 "
1!
#230
0!
#235
b10110 "
1!
#240
0!
#245
b10111 "
1!
#250
0!
#255
b11000 "
1!
#260
0!
#265
b11001 "
1!
#270
0!
#275
b11010 "
1!
#280
0!
#285
b11011 "
1!
#290
0!
#295
b11100 "
1!
#300
0!
#305
b11101 "
1!
#310
0!
#315
b11110 "
1!
#320
0!
#325
b11111 "
1!
#330
0!
#335
b100000 "
1!
#340
0!
#345
b100001 "
1!
#350
0!
#355
b100010 "
1!
#360
0!
#365
b100011 "
1!
#370
0!
#375
b100100 "
1!
#380
0!
#385
b100101 "
1!
#390
0!
#395
b100110 "
1!
#400
0!
#405
b100111 "
1!
#410
0!
#415
b101000 "
1!
#420
0!
#425
b101001 "
1!
#430
0!
#435
b101010 "
1!
#440
0!
#445
b101011 "
1!
#450
0!
#455
b101100 "
1!
#460
0!
#465
b101101 "
1!
#470
0!
#475
b101110 "
1!
#480
0!
#485
b101111 "
1!
#490
0!
#495
b110000 "
1!
#500
0!
#505
b110001 "
1!
#510
0!
#515
b110010 "
1!
#520
0!
#525
b110011 "
1!
#530
0!
#535
b110100 "
1!
#540
0!
#545
b110101 "
1!
#550
0!
#555
b110110 "
1!
#560
0!
#565
b110111 "
1!
#570
0!
#575
b111000 "
1!
#580
0!
#585
b111001 "
1!
#590
0!
#595
b111010 "
1!
#600
0!
#605
b111011 "
1!
#610
0!
#615
b111100 "
1!
#620
0!
#625
b111101 "
1!
#630
0!
#635
b111110 "
1!
#640
0!
#645
b111111 "
1!
#650
0!
#655
b0 "
1!
#660
0!
#665
b1 "
1!
#670
0!
#675
b10 "
1!
#680
0!
#685
b11 "
1!
#690
0!
#695
b100 "
1!
#700
0!
#705
b101 "
1!
#710
0!
#715
b110 "
1!
#720
0!
#725
b111 "
1!
#730
0!
#735
b1000 "
1!
#740
0!
#745
b1001 "
1!
#750
0!
#755
b1010 "
1!
#760
0!
#765
b1011 "
1!
#770
0!
#775
b1100 "
1!
#780
0!
#785
b1101 "
1!
#790
0!
#795
b1110 "
1!
#800
0!
#805
b1111 "
1!
#810
0!
#815
b10000 "
1!
#820
0!
#825
b10001 "
1!
#830
0!
#835
b10010 "
1!
#840
0!
#845
b10011 "
1!
#850
0!
#855
b10100 "
1!
#860
0!
#865
b10101 "
1!
#870
0!
#875
b10110 "
1!
#880
0!
#885
b10111 "
1!
#890
0!
#895
b11000 "
1!
#900
0!
#905
b11001 "
1!
#910
0!
#915
b11010 "
1!
#920
0!
#925
b11011 "
1!
#930
0!
#935
b11100 "
1!
#940
0!
#945
b11101 "
1!
#950
0!
#955
b11110 "
1!
#960
0!
#965
b11111 "
1!
#970
0!
#975
b100000 "
1!
#980
0!
#985
b100001 "
1!
#990
0!
#995
b100010 "
1!
#1000
0!
#1005
b100011 "
1!
#1010
0!
#1015
b100100 "
1!
